spid_sp_test/__init__.py
spid_sp_test/authn_request.py
spid_sp_test/authn_request_extra.py
spid_sp_test/compliant_certificates.py
spid_sp_test/constants.py
spid_sp_test/dump_pem.py
spid_sp_test/exceptions.py
spid_sp_test/html_report.py
spid_sp_test/indicepa.py
spid_sp_test/metadata.py
spid_sp_test/metadata_ag.py
spid_sp_test/metadata_extra.py
spid_sp_test/metadata_private.py
spid_sp_test/metadata_public.py
spid_sp_test/response.py
spid_sp_test/utils.py
spid_sp_test/bin/spid_sp_test
spid_sp_test/html/bootstrap-italia-base.html
spid_sp_test/html/index.html
spid_sp_test/html/static/assets/resizer-3x2.svg
spid_sp_test/html/static/assets/upload-drag-drop-icon.svg
spid_sp_test/html/static/css/bootstrap-italia.min.css
spid_sp_test/html/static/css/bootstrap-italia.min.css.map
spid_sp_test/html/static/fonts/Lora/Lora-Bold.ttf
spid_sp_test/html/static/fonts/Lora/Lora-Bold.woff
spid_sp_test/html/static/fonts/Lora/Lora-Bold.woff2
spid_sp_test/html/static/fonts/Lora/Lora-Regular.ttf
spid_sp_test/html/static/fonts/Lora/Lora-Regular.woff
spid_sp_test/html/static/fonts/Lora/Lora-Regular.woff2
spid_sp_test/html/static/fonts/Lora/OFL.txt
spid_sp_test/html/static/fonts/Roboto_Mono/LICENSE.txt
spid_sp_test/html/static/fonts/Roboto_Mono/RobotoMono-Bold.ttf
spid_sp_test/html/static/fonts/Roboto_Mono/RobotoMono-Bold.woff
spid_sp_test/html/static/fonts/Roboto_Mono/RobotoMono-Bold.woff2
spid_sp_test/html/static/fonts/Roboto_Mono/RobotoMono-Light.ttf
spid_sp_test/html/static/fonts/Roboto_Mono/RobotoMono-Light.woff
spid_sp_test/html/static/fonts/Roboto_Mono/RobotoMono-Light.woff2
spid_sp_test/html/static/fonts/Roboto_Mono/RobotoMono-Medium.ttf
spid_sp_test/html/static/fonts/Roboto_Mono/RobotoMono-Medium.woff
spid_sp_test/html/static/fonts/Roboto_Mono/RobotoMono-Medium.woff2
spid_sp_test/html/static/fonts/Roboto_Mono/RobotoMono-Regular.ttf
spid_sp_test/html/static/fonts/Roboto_Mono/RobotoMono-Regular.woff
spid_sp_test/html/static/fonts/Roboto_Mono/RobotoMono-Regular.woff2
spid_sp_test-1.2.17.dist-info/AUTHORS
spid_sp_test-1.2.17.dist-info/LICENSE
spid_sp_test-1.2.17.dist-info/METADATA
spid_sp_test-1.2.17.dist-info/WHEEL
spid_sp_test-1.2.17.dist-info/top_level.txt
spid_sp_test-1.2.17.dist-info/RECORD
