Metadata-Version: 2.1
Name: spid_sp_test
Version: 1.2.17
Summary: SAML2 SPID/CIE Service Provider validation tool that can be run from the command line
Home-page: https://github.com/italia/spid-sp-test
Author: Giuseppe De Marco
Author-email: giuseppe.demarco@tamdigitale.governo.it
License: License :: OSI Approved :: European Union Public Licence 1.2 (EUPL 1.2)
Classifier: Development Status :: 5 - Production/Stable
Classifier: License :: OSI Approved :: European Union Public Licence 1.2 (EUPL 1.2)
Classifier: Programming Language :: Python :: 3
License-File: LICENSE
License-File: AUTHORS
Requires-Dist: pysaml2 >=6.5.1
Requires-Dist: xmlschema ==1.7.1
Requires-Dist: requests >=2.25.1
Requires-Dist: lxml >=4.6.2
Requires-Dist: Jinja2 >=2.11.3
Requires-Dist: spid-compliant-certificates >=0.5.3
